Metadata-Version: 2.1
Name: ntlmail
Version: 0.0.1
Summary: A SMTP Email Client with NTLP as Authentication
Home-page: 
Author: JJTV1029
Author-email: nicjontrickshots@gmail.com
License: MIT
Keywords: NTLM,SMTP,auth,NTLM SMTP auth,NTLM SMTP,SMTP NTLM
Classifier: Development Status :: 5 - Production/Stable
Classifier: Intended Audience :: Information Technology
Classifier: Operating System :: OS Independent
Classifier: License :: OSI Approved :: MIT License
Classifier: Programming Language :: Python :: 3
Requires: ntlm_auth
Requires: colorama
License-File: LICENSE
